ipydrawio_widgets/__init__.py
ipydrawio_widgets/_version.py
ipydrawio_widgets/constants.py
ipydrawio_widgets/schema.py
ipydrawio_widgets/widget_diagram.py
ipydrawio_widgets/js/package.json
ipydrawio_widgets/js/plugin.json
ipydrawio_widgets-1.3.0.dist-info/LICENSE.txt
ipydrawio_widgets-1.3.0.dist-info/METADATA
ipydrawio_widgets-1.3.0.dist-info/WHEEL
ipydrawio_widgets-1.3.0.dist-info/top_level.txt
ipydrawio_widgets-1.3.0.dist-info/RECORD
